{
  "name": "argon-codebase",
  "tree": {
    "$className": "DataModel",
    "ReplicatedStorage": {
      "$path": "src/Shared",
      "Packages": {
        "$path": "Packages"
      }
    },
    "ReplicatedFirst": {
      "$path": "src/ReplicatedFirst"
    },
    "ServerScriptService": {
      "$path": "src/Server"
    },
    "StarterPlayer": {
      "StarterPlayerScripts": {
        "$path": "src/Client"
      },
      "StarterCharacterScripts": {
        "$path": "src/Character"
      },
      "$properties": {
        "CameraMode": "LockFirstPerson",
        "CharacterUseJumpPower": false,
        "CameraMaxZoomDistance": 128,
        "EnableMouseLockOption": false
      }
    }
  }
}
